Metadata-Version: 2.1
Name: montoenletra
Version: 0.0.8
Summary: Muestra en letras cualquier valor positivo Ej valor cheques
Home-page: https://github.com/myasesor/montoenletra_package
Author: Roger Jose Retamoza Campo
Author-email: myasesor@gmail.com
License: MIT
Keywords: monto en letra,numero a letra
Classifier: Development Status :: 3 - Alpha
Classifier: Intended Audience :: Developers
Classifier: Topic :: Software Development :: Build Tools
Classifier: License :: OSI Approved :: MIT License
Classifier: Programming Language :: Python :: 3
License-File: LICENSE.txt
